[
    {
        "subject": "Бізнес-планування та управління проектами",
        "lecturer": "Якимів А.І., 214 II н.к., ",
        "location": " Практична",
        "urls": [],
        "type": "practical",
        "isFirstWeek": true,
        "isSecondWeek": false,
        "isFirstSubgroup": true,
        "isSecondSubgroup": true,
        "day": 1,
        "number": 5
    },
    {
        "subject": "Бізнес-планування та управління проектами",
        "lecturer": "Лебідь Т.В., 321 I н.к., ",
        "location": " Лекція",
        "urls": [],
        "type": "lection",
        "isFirstWeek": false,
        "isSecondWeek": true,
        "isFirstSubgroup": true,
        "isSecondSubgroup": true,
        "day": 2,
        "number": 6
    }
]