[
    {
        "subject": "Економіко-математичні методи і моделі",
        "lecturer": "Кузяк В.В., 405 IV н.к., ",
        "location": " Лабораторна",
        "urls": [
            "https://us04web.zoom.us/j/75512554898?pwd=5tIRo4PNN6DIootwROShGZ5zsrEooH.1"
        ],
        "type": "lab",
        "isFirstWeek": true,
        "isSecondWeek": true,
        "isFirstSubgroup": true,
        "isSecondSubgroup": false,
        "day": 1,
        "number": 2
    },
    {
        "subject": "Економіко-математичні методи і моделі",
        "lecturer": "Кузяк В.В., 405 IV н.к., ",
        "location": ", Лабораторна",
        "urls": [
            "https://us04web.zoom.us/j/75512554898?pwd=5tIRo4PNN6DIootwROShGZ5zsrEooH.1"
        ],
        "type": "lab",
        "isFirstWeek": true,
        "isSecondWeek": true,
        "isFirstSubgroup": false,
        "isSecondSubgroup": true,
        "day": 1,
        "number": 3
    },
    {
        "subject": "Економіко-математичні методи і моделі",
        "lecturer": "Кузяк В.В., 405 IV н.к., ",
        "location": ", Лабораторна",
        "urls": [
            "https://us04web.zoom.us/j/75512554898?pwd=5tIRo4PNN6DIootwROShGZ5zsrEooH.1"
        ],
        "type": "lab",
        "isFirstWeek": true,
        "isSecondWeek": false,
        "isFirstSubgroup": false,
        "isSecondSubgroup": true,
        "day": 1,
        "number": 4
    },
    {
        "subject": "Економіко-математичні методи і моделі",
        "lecturer": "Кузяк В.В., 405 IV н.к., ",
        "location": " Лабораторна",
        "urls": [
            "https://us04web.zoom.us/j/75512554898?pwd=5tIRo4PNN6DIootwROShGZ5zsrEooH.1"
        ],
        "type": "lab",
        "isFirstWeek": false,
        "isSecondWeek": true,
        "isFirstSubgroup": true,
        "isSecondSubgroup": false,
        "day": 1,
        "number": 4
    },
    {
        "subject": "Інформаційні системи і технології в економіці",
        "lecturer": "Мирощенко Н.Ю., 404 IV н.к., ",
        "location": " Лабораторна",
        "urls": [
            "https://us05web.zoom.us/j/96842633977?pwd=S0ZFajdscW9MS05SZWVTeHkvUytUZz09"
        ],
        "type": "lab",
        "isFirstWeek": true,
        "isSecondWeek": true,
        "isFirstSubgroup": true,
        "isSecondSubgroup": true,
        "day": 1,
        "number": 5
    },
    {
        "subject": "Інформаційні системи і технології в економіці",
        "lecturer": "Воробець С.Й., 206 IV н.к., ",
        "location": " Лекція",
        "urls": [
            "https://us04web.zoom.us/j/5974952318?pwd=S08xYnJQcHBHNlBLRGdVSjRiQkcyQT09"
        ],
        "type": "lection",
        "isFirstWeek": true,
        "isSecondWeek": true,
        "isFirstSubgroup": true,
        "isSecondSubgroup": true,
        "day": 2,
        "number": 1
    },
    {
        "subject": "Фінанси, гроші і кредит",
        "lecturer": "Червінська О.С., 406 IV н.к., ",
        "location": " Лекція",
        "urls": [
            "https://teams.microsoft.com/l/meetup-join/19%3aN_gkKlpYIoOb0s_sUfBHx9ufQ-0j9S-x7gJpkOK6dEo1%40thread.tacv2/1677514194809?context=%7b%22Tid%22%3a%227631cd62-5187-4e15-8b8e-ef653e366e7a%22%2c%22Oid%22%3a%22ce6b48df-85a5-4312-9327-c954e455705c%22%7d"
        ],
        "type": "lection",
        "isFirstWeek": true,
        "isSecondWeek": true,
        "isFirstSubgroup": true,
        "isSecondSubgroup": true,
        "day": 2,
        "number": 2
    },
    {
        "subject": "Економіко-математичні методи і моделі",
        "lecturer": "Гірна О.Б., ",
        "location": " Лекція",
        "urls": [
            "https://us04web.zoom.us/j/77377934096?pwd=95S9BfYOS3kbj8GbUcUe3NPacelMXN.1"
        ],
        "type": "lection",
        "isFirstWeek": true,
        "isSecondWeek": false,
        "isFirstSubgroup": true,
        "isSecondSubgroup": true,
        "day": 2,
        "number": 3
    },
    {
        "subject": "Фінанси, гроші і кредит",
        "lecturer": "Бондаренко Л.П., анг.мовою416 IV н.к., ",
        "location": " Лекція",
        "urls": [],
        "type": "lection",
        "isFirstWeek": true,
        "isSecondWeek": true,
        "isFirstSubgroup": true,
        "isSecondSubgroup": true,
        "day": 2,
        "number": 4
    },
    {
        "subject": "Статистика",
        "lecturer": "Войцеховська Ю.В., 427(1) IV н.к., ",
        "location": " Лабораторна",
        "urls": [],
        "type": "lab",
        "isFirstWeek": false,
        "isSecondWeek": true,
        "isFirstSubgroup": true,
        "isSecondSubgroup": true,
        "day": 3,
        "number": 2
    },
    {
        "subject": "Фінансова діяльність суб`єктів підприємництва",
        "lecturer": "Баланська О.І., 424 IV н.к., ",
        "location": " Практична",
        "urls": [],
        "type": "practical",
        "isFirstWeek": true,
        "isSecondWeek": true,
        "isFirstSubgroup": true,
        "isSecondSubgroup": true,
        "day": 3,
        "number": 3
    },
    {
        "subject": "Національна економіка",
        "lecturer": "Мороз Л.І., 207 IV н.к., ",
        "location": " Практична",
        "urls": [],
        "type": "practical",
        "isFirstWeek": true,
        "isSecondWeek": true,
        "isFirstSubgroup": true,
        "isSecondSubgroup": true,
        "day": 3,
        "number": 4
    },
    {
        "subject": "Фінанси, гроші і кредит",
        "lecturer": "Ливдар М.В., анг.мовою412 IV н.к., ",
        "location": " Практична",
        "urls": [],
        "type": "practical",
        "isFirstWeek": true,
        "isSecondWeek": true,
        "isFirstSubgroup": true,
        "isSecondSubgroup": true,
        "day": 3,
        "number": 5
    },
    {
        "subject": "Фінанси, гроші і кредит",
        "lecturer": "Ливдар М.В., анг.мовою418 IV н.к., ",
        "location": " Лабораторна",
        "urls": [],
        "type": "lab",
        "isFirstWeek": true,
        "isSecondWeek": false,
        "isFirstSubgroup": true,
        "isSecondSubgroup": true,
        "day": 3,
        "number": 6
    },
    {
        "subject": "Фінансова діяльність суб`єктів підприємництва",
        "lecturer": "Селюченко Н.Є., 421 IV н.к., ",
        "location": " Лекція",
        "urls": [
            "http://meet.google.com/trd-puhp-guu"
        ],
        "type": "lection",
        "isFirstWeek": true,
        "isSecondWeek": true,
        "isFirstSubgroup": true,
        "isSecondSubgroup": true,
        "day": 4,
        "number": 2
    },
    {
        "subject": "Національна економіка",
        "lecturer": "Ситник Й.С., 210 IV н.к., ",
        "location": " Лекція",
        "urls": [
            "https://teams.microsoft.com/l/meetup-join/19%3a2660ef2c32294894907449c7543cb82a%40thread.tacv2/1676902949056?context=%7b%22Tid%22%3a%227631cd62-5187-4e15-8b8e-ef653e366e7a%22%2c%22Oid%22%3a%228027bf7f-b55c-40ea-8bd0-4d8ac645413a%22%7d"
        ],
        "type": "lection",
        "isFirstWeek": true,
        "isSecondWeek": true,
        "isFirstSubgroup": true,
        "isSecondSubgroup": true,
        "day": 4,
        "number": 3
    },
    {
        "subject": "Статистика",
        "lecturer": "Войцеховська Ю.В., 416 IV н.к., ",
        "location": " Лекція",
        "urls": [],
        "type": "lection",
        "isFirstWeek": true,
        "isSecondWeek": true,
        "isFirstSubgroup": true,
        "isSecondSubgroup": true,
        "day": 4,
        "number": 4
    },
    {
        "subject": "Фінанси, гроші і кредит",
        "lecturer": "Курило О.Б., 418 IV н.к., ",
        "location": " Лабораторна",
        "urls": [],
        "type": "lab",
        "isFirstWeek": true,
        "isSecondWeek": false,
        "isFirstSubgroup": true,
        "isSecondSubgroup": false,
        "day": 5,
        "number": 1
    },
    {
        "subject": "Фінанси, гроші і кредит",
        "lecturer": "Курило О.Б., 418 IV н.к., ",
        "location": ", Лабораторна",
        "urls": [],
        "type": "lab",
        "isFirstWeek": false,
        "isSecondWeek": true,
        "isFirstSubgroup": false,
        "isSecondSubgroup": true,
        "day": 5,
        "number": 1
    },
    {
        "subject": "Статистика",
        "lecturer": "Бондаренко Ю.Г., 514 IV н.к., ",
        "location": " Практична",
        "urls": [],
        "type": "practical",
        "isFirstWeek": true,
        "isSecondWeek": false,
        "isFirstSubgroup": true,
        "isSecondSubgroup": true,
        "day": 5,
        "number": 2
    },
    {
        "subject": "Фінанси, гроші і кредит",
        "lecturer": "Смірнова Т.О., 423 IV н.к., ",
        "location": " Практична",
        "urls": [],
        "type": "practical",
        "isFirstWeek": true,
        "isSecondWeek": true,
        "isFirstSubgroup": true,
        "isSecondSubgroup": true,
        "day": 5,
        "number": 3
    },
    {
        "subject": "Фізичне виховання, частина 4",
        "lecturer": "Пономарьов С.В., 14.40-16.10, вул. Самчука 11, ",
        "location": " Практична",
        "urls": [],
        "type": "practical",
        "isFirstWeek": true,
        "isSecondWeek": true,
        "isFirstSubgroup": true,
        "isSecondSubgroup": true,
        "day": 5,
        "number": 4
    }
]