[
    {
        "subject": "Мікропроцесорні системи",
        "lecturer": "Пуйда В.Я., ",
        "location": " Лекція",
        "urls": [
            "https://us02web.zoom.us/j/84666210782?pwd=UVp4OFAwN0U2ckltMEQrSStzeStVQT09"
        ],
        "type": "lection",
        "isFirstWeek": true,
        "isSecondWeek": true,
        "isFirstSubgroup": true,
        "isSecondSubgroup": true,
        "day": 1,
        "number": 2
    },
    {
        "subject": "Мікропроцесорні системи",
        "lecturer": "Пуйда В.Я., ",
        "location": " Лекція",
        "urls": [
            "https://us02web.zoom.us/j/84666210782?pwd=UVp4OFAwN0U2ckltMEQrSStzeStVQT09"
        ],
        "type": "lection",
        "isFirstWeek": true,
        "isSecondWeek": true,
        "isFirstSubgroup": true,
        "isSecondSubgroup": true,
        "day": 1,
        "number": 3
    },
    {
        "subject": "Технології опрацювання сигналів і зображень",
        "lecturer": "Лашко О.Л., ",
        "location": " Лекція",
        "urls": [
            "https://us04web.zoom.us/j/79635291150?pwd=bpAtybXan6IzXrfOJntT5bnKaEYbUe.1"
        ],
        "type": "lection",
        "isFirstWeek": true,
        "isSecondWeek": true,
        "isFirstSubgroup": true,
        "isSecondSubgroup": true,
        "day": 1,
        "number": 4
    },
    {
        "subject": "Засоби програмної віртуалізації",
        "lecturer": "Наконечний Р.А., ",
        "location": " Лекція",
        "urls": [
            "https://us04web.zoom.us/j/2878103205?pwd=Zjc1enNRb2FVZ3lxYkF1b3dCWjVVdz09"
        ],
        "type": "lection",
        "isFirstWeek": true,
        "isSecondWeek": true,
        "isFirstSubgroup": true,
        "isSecondSubgroup": true,
        "day": 1,
        "number": 5
    },
    {
        "subject": "Засоби програмної віртуалізації",
        "lecturer": "Наконечний Р.А., ",
        "location": " Лекція",
        "urls": [
            "https://us04web.zoom.us/j/2878103205?pwd=Zjc1enNRb2FVZ3lxYkF1b3dCWjVVdz09"
        ],
        "type": "lection",
        "isFirstWeek": true,
        "isSecondWeek": false,
        "isFirstSubgroup": true,
        "isSecondSubgroup": true,
        "day": 1,
        "number": 6
    },
    {
        "subject": "Засоби програмної віртуалізації",
        "lecturer": "Наконечний Р.А., ",
        "location": ", Лабораторна",
        "urls": [
            "https://us04web.zoom.us/j/2878103205?pwd=Zjc1enNRb2FVZ3lxYkF1b3dCWjVVdz09"
        ],
        "type": "lab",
        "isFirstWeek": true,
        "isSecondWeek": true,
        "isFirstSubgroup": false,
        "isSecondSubgroup": true,
        "day": 2,
        "number": 3
    },
    {
        "subject": "Засоби програмної віртуалізації",
        "lecturer": "Наконечний Р.А., ",
        "location": " Лабораторна",
        "urls": [
            "https://us04web.zoom.us/j/2878103205?pwd=Zjc1enNRb2FVZ3lxYkF1b3dCWjVVdz09"
        ],
        "type": "lab",
        "isFirstWeek": true,
        "isSecondWeek": true,
        "isFirstSubgroup": true,
        "isSecondSubgroup": false,
        "day": 2,
        "number": 4
    },
    {
        "subject": "Веб програмування",
        "lecturer": "Муляревич О.В., ",
        "location": ", Лабораторна",
        "urls": [
            "https://us04web.zoom.us/j/6873499091?pwd=amVFZWthTTR6anhuYVhQSkhQWVpEdz09"
        ],
        "type": "lab",
        "isFirstWeek": true,
        "isSecondWeek": true,
        "isFirstSubgroup": false,
        "isSecondSubgroup": true,
        "day": 2,
        "number": 6
    },
    {
        "subject": "Системи управління базами даних",
        "lecturer": "Колодчак О.М., ",
        "location": " Лабораторна",
        "urls": [
            "https://us04web.zoom.us/j/8790946798?pwd=cVg0NFBSS2xRcTZmTHc0bFBPcEZGZz09"
        ],
        "type": "lab",
        "isFirstWeek": false,
        "isSecondWeek": true,
        "isFirstSubgroup": true,
        "isSecondSubgroup": true,
        "day": 3,
        "number": 1
    },
    {
        "subject": "Системи управління базами даних",
        "lecturer": "Колодчак О.М., ",
        "location": " Лекція",
        "urls": [
            "https://us04web.zoom.us/j/8790946798?pwd=cVg0NFBSS2xRcTZmTHc0bFBPcEZGZz09"
        ],
        "type": "lection",
        "isFirstWeek": false,
        "isSecondWeek": true,
        "isFirstSubgroup": true,
        "isSecondSubgroup": true,
        "day": 3,
        "number": 2
    },
    {
        "subject": "Системи управління базами даних",
        "lecturer": "Колодчак О.М., ",
        "location": " Лабораторна",
        "urls": [
            "https://us04web.zoom.us/j/8790946798?pwd=cVg0NFBSS2xRcTZmTHc0bFBPcEZGZz09"
        ],
        "type": "lab",
        "isFirstWeek": true,
        "isSecondWeek": false,
        "isFirstSubgroup": true,
        "isSecondSubgroup": true,
        "day": 3,
        "number": 2
    },
    {
        "subject": "Системи управління базами даних",
        "lecturer": "Колодчак О.М., ",
        "location": " Лекція",
        "urls": [
            "https://us04web.zoom.us/j/8790946798?pwd=cVg0NFBSS2xRcTZmTHc0bFBPcEZGZz09"
        ],
        "type": "lection",
        "isFirstWeek": true,
        "isSecondWeek": true,
        "isFirstSubgroup": true,
        "isSecondSubgroup": true,
        "day": 3,
        "number": 3
    },
    {
        "subject": "Веб програмування",
        "lecturer": "Колодчак О.М., ",
        "location": " Лекція",
        "urls": [
            "https://us04web.zoom.us/j/8790946798?pwd=cVg0NFBSS2xRcTZmTHc0bFBPcEZGZz09"
        ],
        "type": "lection",
        "isFirstWeek": true,
        "isSecondWeek": true,
        "isFirstSubgroup": true,
        "isSecondSubgroup": true,
        "day": 3,
        "number": 4
    },
    {
        "subject": "Веб програмування",
        "lecturer": "Колодчак О.М., ",
        "location": " Лекція",
        "urls": [
            "https://us04web.zoom.us/j/6873499091?pwd=amVFZWthTTR6anhuYVhQSkhQWVpEdz09"
        ],
        "type": "lection",
        "isFirstWeek": true,
        "isSecondWeek": false,
        "isFirstSubgroup": true,
        "isSecondSubgroup": true,
        "day": 3,
        "number": 5
    },
    {
        "subject": "Технології опрацювання сигналів і зображень",
        "lecturer": "Лашко О.Л., ",
        "location": " Лекція",
        "urls": [
            "https://us04web.zoom.us/j/79635291150?pwd=bpAtybXan6IzXrfOJntT5bnKaEYbUe.1"
        ],
        "type": "lection",
        "isFirstWeek": false,
        "isSecondWeek": true,
        "isFirstSubgroup": true,
        "isSecondSubgroup": true,
        "day": 3,
        "number": 5
    },
    {
        "subject": "Технології опрацювання сигналів і зображень",
        "lecturer": "Лашко О.Л., ",
        "location": " Лекція",
        "urls": [
            "https://us04web.zoom.us/j/79635291150?pwd=bpAtybXan6IzXrfOJntT5bnKaEYbUe.1"
        ],
        "type": "lection",
        "isFirstWeek": true,
        "isSecondWeek": false,
        "isFirstSubgroup": true,
        "isSecondSubgroup": true,
        "day": 3,
        "number": 6
    },
    {
        "subject": "Технології опрацювання сигналів і зображень",
        "lecturer": "Грицик І.В., ",
        "location": " Лабораторна",
        "urls": [
            "https://meet.google.com/hcq-egrb-iap"
        ],
        "type": "lab",
        "isFirstWeek": true,
        "isSecondWeek": true,
        "isFirstSubgroup": true,
        "isSecondSubgroup": false,
        "day": 4,
        "number": 1
    },
    {
        "subject": "Технології опрацювання сигналів і зображень",
        "lecturer": "Грицик І.В., ",
        "location": ", Лабораторна",
        "urls": [
            "https://tel.meet/jgx-ekzg-vuw"
        ],
        "type": "lab",
        "isFirstWeek": true,
        "isSecondWeek": true,
        "isFirstSubgroup": false,
        "isSecondSubgroup": true,
        "day": 4,
        "number": 2
    },
    {
        "subject": "Мікропроцесорні системи",
        "lecturer": "Парамуд Я.С., ",
        "location": " Лабораторна",
        "urls": [
            "https://us04web.zoom.us/j/79398877475?pwd=NUFBWHp6NU5PekMxdzFsS0tJSURpZz09"
        ],
        "type": "lab",
        "isFirstWeek": true,
        "isSecondWeek": true,
        "isFirstSubgroup": true,
        "isSecondSubgroup": false,
        "day": 4,
        "number": 2
    },
    {
        "subject": "Мікропроцесорні системи",
        "lecturer": "Парамуд Я.С., ",
        "location": ", Лабораторна",
        "urls": [
            "https://us04web.zoom.us/j/79398877475?pwd=NUFBWHp6NU5PekMxdzFsS0tJSURpZz09"
        ],
        "type": "lab",
        "isFirstWeek": true,
        "isSecondWeek": true,
        "isFirstSubgroup": false,
        "isSecondSubgroup": true,
        "day": 4,
        "number": 3
    },
    {
        "subject": "Веб програмування",
        "lecturer": "Муляревич О.В., ",
        "location": " Лабораторна",
        "urls": [
            "https://us04web.zoom.us/j/6873499091?pwd=amVFZWthTTR6anhuYVhQSkhQWVpEdz09"
        ],
        "type": "lab",
        "isFirstWeek": true,
        "isSecondWeek": true,
        "isFirstSubgroup": true,
        "isSecondSubgroup": false,
        "day": 6,
        "number": 1
    }
]