[
    {
        "subject": "Технології вебкартографування",
        "lecturer": "Юрків М.І., ",
        "location": " Лекція",
        "urls": [
            "https://us04web.zoom.us/j/74825980149?pwd=M2tEeLHSvBfsZd8MwbuE819YALpf7u.1"
        ],
        "type": "lection",
        "isFirstWeek": true,
        "isSecondWeek": true,
        "isFirstSubgroup": true,
        "isSecondSubgroup": true,
        "day": 1,
        "number": 3
    },
    {
        "subject": "Математико-статистичні методи в картографії",
        "lecturer": "Бридун А.М., ",
        "location": " Лекція",
        "urls": [
            "https://us04web.zoom.us/j/9135684222?pwd=4YBaVRLlq0CllYntfb5eV1rbVq3BIQ.1"
        ],
        "type": "lection",
        "isFirstWeek": true,
        "isSecondWeek": true,
        "isFirstSubgroup": true,
        "isSecondSubgroup": true,
        "day": 1,
        "number": 4
    },
    {
        "subject": "Картографічне моделювання",
        "lecturer": "Бридун А.М., ",
        "location": " Лекція",
        "urls": [
            "https://us04web.zoom.us/j/9135684222?pwd=4YBaVRLlq0CllYntfb5eV1rbVq3BIQ.1"
        ],
        "type": "lection",
        "isFirstWeek": true,
        "isSecondWeek": false,
        "isFirstSubgroup": true,
        "isSecondSubgroup": true,
        "day": 2,
        "number": 1
    },
    {
        "subject": "Геоінформаційне картографування",
        "lecturer": "Андрейчук Ю.М., Голубінка Ю.І., 611 II н.к., ",
        "location": " Лабораторна",
        "urls": [
            "https://us04web.zoom.us/j/5105514305?pwd=N2VlREQ2cXRNejFBL2F5WStsZWlmUT09"
        ],
        "type": "lab",
        "isFirstWeek": true,
        "isSecondWeek": true,
        "isFirstSubgroup": true,
        "isSecondSubgroup": true,
        "day": 2,
        "number": 3
    },
    {
        "subject": "Геоінформаційне картографування",
        "lecturer": "Андрейчук Ю.М., 612 II н.к., ",
        "location": " Лекція",
        "urls": [
            "https://us04web.zoom.us/j/5105514305?pwd=N2VlREQ2cXRNejFBL2F5WStsZWlmUT09"
        ],
        "type": "lection",
        "isFirstWeek": false,
        "isSecondWeek": true,
        "isFirstSubgroup": true,
        "isSecondSubgroup": true,
        "day": 2,
        "number": 4
    },
    {
        "subject": "Технології вебкартографування",
        "lecturer": "Голубінка Ю.І., Юрків М.І., 608 II н.к., ",
        "location": " Лабораторна",
        "urls": [
            "https://us04web.zoom.us/j/74825980149?pwd=M2tEeLHSvBfsZd8MwbuE819YALpf7u.1"
        ],
        "type": "lab",
        "isFirstWeek": true,
        "isSecondWeek": true,
        "isFirstSubgroup": true,
        "isSecondSubgroup": true,
        "day": 3,
        "number": 2
    },
    {
        "subject": "Картографічне моделювання",
        "lecturer": "Бридун А.М., Фис М.М., 609 II н.к., ",
        "location": " Лабораторна",
        "urls": [
            "https://us04web.zoom.us/j/9135684222?pwd=4YBaVRLlq0CllYntfb5eV1rbVq3BIQ.1"
        ],
        "type": "lab",
        "isFirstWeek": true,
        "isSecondWeek": true,
        "isFirstSubgroup": true,
        "isSecondSubgroup": true,
        "day": 3,
        "number": 3
    },
    {
        "subject": "Математико-статистичні методи в картографії",
        "lecturer": "Бридун А.М., Фис М.М., 609 II н.к., ",
        "location": " Лабораторна",
        "urls": [
            "https://us04web.zoom.us/j/9135684222?pwd=4YBaVRLlq0CllYntfb5eV1rbVq3BIQ.1",
            "https://zoom.us/j/96482066240?pwd=RlFWbHMyVHYyOXFzYjByMGNNVDdIZz09"
        ],
        "type": "lab",
        "isFirstWeek": true,
        "isSecondWeek": false,
        "isFirstSubgroup": true,
        "isSecondSubgroup": true,
        "day": 3,
        "number": 4
    }
]