[
    {
        "subject": "Соціальна психологія, частина 1",
        "lecturer": "Борисенко О.М., 27 XXXIII н.к., ",
        "location": " Практична",
        "urls": [],
        "type": "practical",
        "isFirstWeek": true,
        "isSecondWeek": true,
        "isFirstSubgroup": true,
        "isSecondSubgroup": true,
        "day": 1,
        "number": 4
    },
    {
        "subject": "Анатомія та фізіологія центральної нервової системи",
        "lecturer": "Колінковський27 XXXIII н.к., ",
        "location": " Практична",
        "urls": [],
        "type": "practical",
        "isFirstWeek": true,
        "isSecondWeek": true,
        "isFirstSubgroup": true,
        "isSecondSubgroup": true,
        "day": 1,
        "number": 5
    },
    {
        "subject": "Соціальна психологія, частина 1",
        "lecturer": "Борисюк О.М., 34 XXXIII н.к., ",
        "location": " Лекція",
        "urls": [],
        "type": "lection",
        "isFirstWeek": false,
        "isSecondWeek": true,
        "isFirstSubgroup": true,
        "isSecondSubgroup": true,
        "day": 2,
        "number": 2
    },
    {
        "subject": "Соціальна психологія, частина 1",
        "lecturer": "Борисюк О.М., 34 XXXIII н.к., ",
        "location": " Лекція",
        "urls": [],
        "type": "lection",
        "isFirstWeek": true,
        "isSecondWeek": true,
        "isFirstSubgroup": true,
        "isSecondSubgroup": true,
        "day": 2,
        "number": 3
    },
    {
        "subject": "Анатомія та фізіологія центральної нервової системи",
        "lecturer": "Галян І.М., 313 XIX н.к., ",
        "location": " Лекція",
        "urls": [],
        "type": "lection",
        "isFirstWeek": true,
        "isSecondWeek": true,
        "isFirstSubgroup": true,
        "isSecondSubgroup": true,
        "day": 2,
        "number": 4
    },
    {
        "subject": "Іноземна мова за професійним спрямуванням, частина 2",
        "lecturer": "Бусько М.Б., 42 VII н.к., ",
        "location": ", Практична",
        "urls": [],
        "type": "practical",
        "isFirstWeek": false,
        "isSecondWeek": true,
        "isFirstSubgroup": false,
        "isSecondSubgroup": true,
        "day": 3,
        "number": 1
    },
    {
        "subject": "Іноземна мова за професійним спрямуванням, частина 2",
        "lecturer": "Гук Л.І., 45 VII н.к., ",
        "location": " Практична",
        "urls": [],
        "type": "practical",
        "isFirstWeek": true,
        "isSecondWeek": true,
        "isFirstSubgroup": true,
        "isSecondSubgroup": false,
        "day": 3,
        "number": 1
    },
    {
        "subject": "Іноземна мова за професійним спрямуванням, частина 2",
        "lecturer": "Бусько М.Б., 42 VII н.к., ",
        "location": ", Практична",
        "urls": [],
        "type": "practical",
        "isFirstWeek": true,
        "isSecondWeek": false,
        "isFirstSubgroup": false,
        "isSecondSubgroup": true,
        "day": 3,
        "number": 2
    },
    {
        "subject": "Іноземна мова за професійним спрямуванням, частина 2",
        "lecturer": "Бусько М.Б., 32 VII н.к., ",
        "location": ", Практична",
        "urls": [],
        "type": "practical",
        "isFirstWeek": false,
        "isSecondWeek": true,
        "isFirstSubgroup": false,
        "isSecondSubgroup": true,
        "day": 3,
        "number": 2
    },
    {
        "subject": "Іноземна мова за професійним спрямуванням, частина 2",
        "lecturer": "Гук Л.І., 45 VII н.к., ",
        "location": " Практична",
        "urls": [],
        "type": "practical",
        "isFirstWeek": true,
        "isSecondWeek": false,
        "isFirstSubgroup": true,
        "isSecondSubgroup": false,
        "day": 3,
        "number": 2
    },
    {
        "subject": "Українська мова (за професійним спрямуванням)",
        "lecturer": "Пура Я.С., 328 XIX н.к., ",
        "location": " Практична",
        "urls": [],
        "type": "practical",
        "isFirstWeek": true,
        "isSecondWeek": true,
        "isFirstSubgroup": true,
        "isSecondSubgroup": true,
        "day": 3,
        "number": 3
    },
    {
        "subject": "Фізичне виховання, частина 2",
        "lecturer": "Гулей К.С., Самчука 11. 8.00-9.30",
        "location": " Практична",
        "urls": [],
        "type": "practical",
        "isFirstWeek": true,
        "isSecondWeek": true,
        "isFirstSubgroup": true,
        "isSecondSubgroup": true,
        "day": 4,
        "number": 1
    },
    {
        "subject": "Загальна психологія , частина 2",
        "lecturer": "Новікова Ж.М., 116 XX н.к., ",
        "location": " Практична",
        "urls": [],
        "type": "practical",
        "isFirstWeek": true,
        "isSecondWeek": true,
        "isFirstSubgroup": true,
        "isSecondSubgroup": true,
        "day": 4,
        "number": 2
    },
    {
        "subject": "Загальна психологія , частина 2",
        "lecturer": "Новікова Ж.М., 116 XX н.к., ",
        "location": " Практична",
        "urls": [],
        "type": "practical",
        "isFirstWeek": true,
        "isSecondWeek": true,
        "isFirstSubgroup": true,
        "isSecondSubgroup": true,
        "day": 4,
        "number": 3
    },
    {
        "subject": "Психологія особистості",
        "lecturer": "Бакаїм Ю.М., 116 XX н.к., ",
        "location": " Практична",
        "urls": [],
        "type": "practical",
        "isFirstWeek": true,
        "isSecondWeek": true,
        "isFirstSubgroup": true,
        "isSecondSubgroup": true,
        "day": 4,
        "number": 4
    },
    {
        "subject": "Психологія особистості",
        "lecturer": "Олійник А.В., 313 XIX н.к., ",
        "location": " Лекція",
        "urls": [
            "https://teams.microsoft.com/l/message/19:QA9nWxeC5hFJnYz0LipDdYL-VbX5I5GMGrFlzLJ1UHE1@thread.tacv2/1686811099176?groupId=96d25e0e-6e97-41b9-aaa4-44d16eeeeaaf"
        ],
        "type": "lection",
        "isFirstWeek": true,
        "isSecondWeek": true,
        "isFirstSubgroup": true,
        "isSecondSubgroup": true,
        "day": 5,
        "number": 2
    },
    {
        "subject": "Психологія особистості",
        "lecturer": "Олійник А.В., 313 XIX н.к., ",
        "location": " Лекція",
        "urls": [
            "https://teams.microsoft.com/l/message/19:QA9nWxeC5hFJnYz0LipDdYL-VbX5I5GMGrFlzLJ1UHE1@thread.tacv2/1686811099176?groupId=96d25e0e-6e97-41b9-aaa4-44d16eeeeaaf"
        ],
        "type": "lection",
        "isFirstWeek": true,
        "isSecondWeek": true,
        "isFirstSubgroup": true,
        "isSecondSubgroup": true,
        "day": 5,
        "number": 3
    },
    {
        "subject": "Загальна психологія , частина 2",
        "lecturer": "Мащак С.О., 313 XIX н.к., ",
        "location": " Лекція",
        "urls": [],
        "type": "lection",
        "isFirstWeek": true,
        "isSecondWeek": true,
        "isFirstSubgroup": true,
        "isSecondSubgroup": true,
        "day": 5,
        "number": 4
    },
    {
        "subject": "Загальна психологія , частина 2",
        "lecturer": "Мащак С.О., 313 XIX н.к., ",
        "location": " Лекція",
        "urls": [],
        "type": "lection",
        "isFirstWeek": true,
        "isSecondWeek": true,
        "isFirstSubgroup": true,
        "isSecondSubgroup": true,
        "day": 5,
        "number": 5
    }
]